enterprise_docs/__init__.py
enterprise_docs/banner.py
enterprise_docs/cli.py
enterprise_docs/templates/ARCHITECTURE.md
enterprise_docs/templates/BUG_REPORT.md
enterprise_docs/templates/CHANGELOG.md
enterprise_docs/templates/CODE_OF_CONDUCT.md
enterprise_docs/templates/COMPLIANCE.md
enterprise_docs/templates/CONTRIBUTING.md
enterprise_docs/templates/COPYRIGHT_DISCLAIMER.md
enterprise_docs/templates/DATA_PRIVACY.md
enterprise_docs/templates/DEPENDENCY_POLICY.md
enterprise_docs/templates/DEPRECATION_POLICY.md
enterprise_docs/templates/DEVELOPER_GUIDE.md
enterprise_docs/templates/DOCUMENTATION_OVERVIEW.md
enterprise_docs/templates/FAIR_USE_POLICIES.md
enterprise_docs/templates/FEATURE_REQUEST.md
enterprise_docs/templates/GOVERNANCE.md
enterprise_docs/templates/MAINTAINERS.md
enterprise_docs/templates/ONBOARDING.md
enterprise_docs/templates/PULL_REQUEST_TEMPLATE.md
enterprise_docs/templates/RELEASES.md
enterprise_docs/templates/RELEASE_POLICY.md
enterprise_docs/templates/RISK_REGISTER.md
enterprise_docs/templates/ROADMAP.md
enterprise_docs/templates/SECURITY.md
enterprise_docs/templates/SECURITY_AUDIT_CHECKLIST.md
enterprise_docs/templates/SECURITY_POLICY.md
enterprise_docs/templates/SECURITY_RESPONSE_PLAYBOOK.md
enterprise_docs/templates/SUPPORT.md
enterprise_docs/templates/SUPPORT_MATRIX.md
enterprise_docs/templates/TESTING_STRATEGY.md
enterprise_docs/templates/THREAT_MODEL.md
enterprise_docs/templates/TRADEMARK_AND_BRANDING_POLICIES.md
enterprise_docs/templates/USER_GUIDELINES.md
enterprise_docs/templates/__init__.py
enterprise_docs/templates/default_CODEOWNERS
enterprise_docs/templates/default_FEATURE_REQUEST.md
enterprise_docs/templates/default_LICENSE
enterprise_docs/templates/default_NOTICE
enterprise_docs/templates/default_TRADEMARK_AND_BRANDING_POLICIES.md
enterprise_docs/templates/default_publish.yml
enterprise_docs/templates/default_pyproject.toml
enterprise_docs-4.0.1.dist-info/licenses/LICENSE
enterprise_docs-4.0.1.dist-info/METADATA
enterprise_docs-4.0.1.dist-info/WHEEL
enterprise_docs-4.0.1.dist-info/entry_points.txt
enterprise_docs-4.0.1.dist-info/top_level.txt
enterprise_docs-4.0.1.dist-info/RECORD
