Metadata-Version: 2.4
Name: enterprise-docs
Version: 4.0.1
Summary: Unified enterprise documentation suite for Dhruv13x organization — providing policy, compliance, and automation templates for enterprise-grade Python projects.
Author-email: Dhruv <dhruv13x@gmail.com>
Maintainer-email: Dhruv <dhruv13x@gmail.com>
License: MIT
Project-URL: Homepage, https://github.com/dhruv13x/enterprise-docs
Project-URL: Repository, https://github.com/dhruv13x/enterprise-docs.git
Project-URL: Documentation, https://github.com/dhruv13x/enterprise-docs/tree/main/docs
Project-URL: Issues, https://github.com/dhruv13x/enterprise-docs/issues
Project-URL: Changelog, https://github.com/dhruv13x/enterprise-docs/blob/main/CHANGELOG.md
Project-URL: Release Notes, https://github.com/dhruv13x/enterprise-docs/releases
Keywords: documentation,policy,templates,enterprise,compliance,automation
Classifier: Development Status :: 5 - Production/Stable
Classifier: Intended Audience :: Developers
Classifier: Topic :: Software Development :: Documentation
Classifier: Topic :: Software Development :: Quality Assurance
Classifier: License :: OSI Approved :: MIT License
Classifier: Operating System :: OS Independent
Classifier: Programming Language :: Python :: 3
Classifier: Programming Language :: Python :: 3.12
Classifier: Programming Language :: Python :: 3 :: Only
Classifier: Typing :: Typed
Requires-Python: >=3.10
License-File: LICENSE
Requires-Dist: rich>=13.0
Provides-Extra: dev
Requires-Dist: pytest>=8.0.0; extra == "dev"
Requires-Dist: pytest-cov>=5.0.0; extra == "dev"
Requires-Dist: pytest-timeout>=2.2.0; extra == "dev"
Requires-Dist: pytest-json-report>=1.5.0; extra == "dev"
Requires-Dist: pytest-asyncio>=0.23.0; extra == "dev"
Requires-Dist: pytest-mock>=3.10.0; extra == "dev"
Requires-Dist: pyfakefs>=5.0.0; extra == "dev"
Requires-Dist: ruff>=0.6.0; extra == "dev"
Requires-Dist: black>=24.3.0; extra == "dev"
Requires-Dist: mypy>=1.11.0; extra == "dev"
Requires-Dist: PyYAML>=6.0; extra == "dev"
Requires-Dist: types-PyYAML>=6.0; extra == "dev"
Provides-Extra: docs
Requires-Dist: sphinx>=7.0; extra == "docs"
Requires-Dist: sphinx-rtd-theme>=2.0; extra == "docs"
Provides-Extra: test
Requires-Dist: pytest>=8.0; extra == "test"
Requires-Dist: pytest-cov>=5.0; extra == "test"
Dynamic: license-file
